limited_shell-0.10.10.data/data/etc/lshell.conf
limited_shell-0.10.10.data/data/etc/logrotate.d/lshell
limited_shell-0.10.10.data/data/share/doc/lshell/CHANGELOG.md
limited_shell-0.10.10.data/data/share/doc/lshell/COPYING
limited_shell-0.10.10.data/data/share/doc/lshell/README.md
limited_shell-0.10.10.data/data/share/doc/lshell/SECURITY.md
limited_shell-0.10.10.data/data/share/man/man1/lshell.1
limited_shell-0.10.10.data/scripts/lshell
lshell/__init__.py
lshell/builtincmd.py
lshell/checkconfig.py
lshell/completion.py
lshell/sec.py
lshell/shellcmd.py
lshell/utils.py
lshell/variables.py
limited_shell-0.10.10.dist-info/COPYING
limited_shell-0.10.10.dist-info/METADATA
limited_shell-0.10.10.dist-info/WHEEL
limited_shell-0.10.10.dist-info/top_level.txt
limited_shell-0.10.10.dist-info/RECORD
