Metadata-Version: 2.1
Name: limited-shell
Version: 0.10.10
Summary: lshell - Limited Shell
Home-page: https://github.com/ghantoos/lshell
Author: Ignace Mouzannar
Author-email: ghantoos@ghantoos.org
Maintainer: Ignace Mouzannar
Maintainer-email: ghantoos@ghantoos.org
License: GPL-3
Project-URL: GitHub, https://github.com/ghantoos/lshell
Project-URL: Changelog, https://github.com/ghantoos/lshell/blob/master/CHANGELOG.md
Keywords: limited,shell,security,python
Platform: UNIX
Classifier: Development Status :: 5 - Production/Stable
Classifier: Environment :: Console
Classifier: Intended Audience :: Information Technology
Classifier: Intended Audience :: System Administrators
Classifier: License :: OSI Approved :: GNU General Public License v3 (GPLv3)
Classifier: Operating System :: POSIX
Classifier: Programming Language :: Python :: 3
Classifier: Topic :: Security
Classifier: Topic :: System :: Shells
Classifier: Topic :: System :: System Shells
Classifier: Topic :: System :: Systems Administration
Classifier: Topic :: Terminals
Requires-Python: >=3.6
License-File: COPYING
